{
    "TextDetections": [
        {
            "DetectedText": "2017-12-11 AM 54:50",
            "Type": "LINE",
            "Id": 0,
            "Confidence": 90.03177642822266,
            "Geometry": {
                "BoundingBox": {
                    "Width": 0.505783200263977,
                    "Height": 0.05606021732091904,
                    "Left": -0.0033477405086159706,
                    "Top": 0.02221435122191906
                },
                "Polygon": [
                    {
                        "X": -0.0033477405086159706,
                        "Y": 0.02221435122191906
                    },
                    {
                        "X": 0.5024354457855225,
                        "Y": 0.02257271111011505
                    },
                    {
                        "X": 0.5024141073226929,
                        "Y": 0.07863292843103409
                    },
                    {
                        "X": -0.0033690789714455605,
                        "Y": 0.07827457040548325
                    }
                ]
            }
        },
        {
            "DetectedText": "Entrance",
            "Type": "LINE",
            "Id": 1,
            "Confidence": 98.24291229248047,
            "Geometry": {
                "BoundingBox": {
                    "Width": 0.21314308047294617,
                    "Height": 0.06661771982908249,
                    "Left": 0.0016442547785118222,
                    "Top": 0.1164068877696991
                },
                "Polygon": [
                    {
                        "X": 0.0016442547785118222,
                        "Y": 0.1164068877696991
                    },
                    {
                        "X": 0.2147873342037201,
                        "Y": 0.11590900272130966
                    },
                    {
                        "X": 0.21487092971801758,
                        "Y": 0.18252672255039215
                    },
                    {
                        "X": 0.0017278539016842842,
                        "Y": 0.183024600148201
                    }
                ]
            }
        },
        {
            "DetectedText": "2017-12-11",
            "Type": "WORD",
            "Id": 2,
            "ParentId": 0,
            "Confidence": 86.31270599365234,
            "Geometry": {
                "BoundingBox": {
                    "Width": 0.22618138790130615,
                    "Height": 0.054334212094545364,
                    "Left": 0.0,
                    "Top": 0.023141395300626755
                },
                "Polygon": [
                    {
                        "X": -0.00334802339784801,
                        "Y": 0.022957729175686836
                    },
                    {
                        "X": 0.22748112678527832,
                        "Y": 0.022610994055867195
                    },
                    {
                        "X": 0.22752508521080017,
                        "Y": 0.07708010077476501
                    },
                    {
                        "X": -0.003304067999124527,
                        "Y": 0.07742683589458466
                    }
                ]
            }
        },
        {
            "DetectedText": "AM",
            "Type": "WORD",
            "Id": 3,
            "ParentId": 0,
            "Confidence": 95.71389770507812,
            "Geometry": {
                "BoundingBox": {
                    "Width": 0.050353825092315674,
                    "Height": 0.05511505901813507,
                    "Left": 0.24858137965202332,
                    "Top": 0.023353269323706627
                },
                "Polygon": [
                    {
                        "X": 0.24842382967472076,
                        "Y": 0.02353809028863907
                    },
                    {
                        "X": 0.29907217621803284,
                        "Y": 0.023273473605513573
                    },
                    {
                        "X": 0.29922595620155334,
                        "Y": 0.07806091010570526
                    },
                    {
                        "X": 0.24857760965824127,
                        "Y": 0.07832552492618561
                    }
                ]
            }
        },
        {
            "DetectedText": "54:50",
            "Type": "WORD",
            "Id": 4,
            "ParentId": 0,
            "Confidence": 88.0687255859375,
            "Geometry": {
                "BoundingBox": {
                    "Width": 0.11914604902267456,
                    "Height": 0.055993083864450455,
                    "Left": 0.3836492896080017,
                    "Top": 0.022502850741147995
                },
                "Polygon": [
                    {
                        "X": 0.3836928904056549,
                        "Y": 0.023237494751811028
                    },
                    {
                        "X": 0.5022477507591248,
                        "Y": 0.022572578862309456
                    },
                    {
                        "X": 0.5024144053459167,
                        "Y": 0.0778840184211731
                    },
                    {
                        "X": 0.3838595449924469,
                        "Y": 0.07854893058538437
                    }
                ]
            }
        },
        {
            "DetectedText": "Entrance",
            "Type": "WORD",
            "Id": 5,
            "ParentId": 1,
            "Confidence": 98.24291229248047,
            "Geometry": {
                "BoundingBox": {
                    "Width": 0.2130952775478363,
                    "Height": 0.0676717683672905,
                    "Left": 0.0019297823309898376,
                    "Top": 0.11583403497934341
                },
                "Polygon": [
                    {
                        "X": 0.0016442547785118222,
                        "Y": 0.1164068877696991
                    },
                    {
                        "X": 0.2147873342037201,
                        "Y": 0.11590900272130966
                    },
                    {
                        "X": 0.21487092971801758,
                        "Y": 0.18252672255039215
                    },
                    {
                        "X": 0.0017278539016842842,
                        "Y": 0.183024600148201
                    }
                ]
            }
        }
    ]
}
