{
    "TextDetections": [
        {
            "DetectedText": "2017-12-11 AM 03:54:",
            "Type": "LINE",
            "Id": 0,
            "Confidence": 90.88837432861328,
            "Geometry": {
                "BoundingBox": {
                    "Width": 0.447486937046051,
                    "Height": 0.057555053383111954,
                    "Left": -0.0033084722235798836,
                    "Top": 0.021496644243597984
                },
                "Polygon": [
                    {
                        "X": -0.0033084722235798836,
                        "Y": 0.021496644243597984
                    },
                    {
                        "X": 0.4441784620285034,
                        "Y": 0.022287949919700623
                    },
                    {
                        "X": 0.444123774766922,
                        "Y": 0.07984300702810287
                    },
                    {
                        "X": -0.0033631487749516964,
                        "Y": 0.07905169576406479
                    }
                ]
            }
        },
        {
            "DetectedText": "Entrance",
            "Type": "LINE",
            "Id": 1,
            "Confidence": 97.85722351074219,
            "Geometry": {
                "BoundingBox": {
                    "Width": 0.2129814475774765,
                    "Height": 0.06703334301710129,
                    "Left": 0.0018622541101649404,
                    "Top": 0.11625657230615616
                },
                "Polygon": [
                    {
                        "X": 0.0018622541101649404,
                        "Y": 0.11625657230615616
                    },
                    {
                        "X": 0.21484370529651642,
                        "Y": 0.11555112898349762
                    },
                    {
                        "X": 0.21496298909187317,
                        "Y": 0.1825844794511795
                    },
                    {
                        "X": 0.0019815333653241396,
                        "Y": 0.18328991532325745
                    }
                ]
            }
        },
        {
            "DetectedText": "Jn",
            "Type": "LINE",
            "Id": 2,
            "Confidence": 51.01042556762695,
            "Geometry": {
                "BoundingBox": {
                    "Width": 0.06210613250732422,
                    "Height": 0.05318653956055641,
                    "Left": 0.8185522556304932,
                    "Top": 0.752349317073822
                },
                "Polygon": [
                    {
                        "X": 0.8185522556304932,
                        "Y": 0.752349317073822
                    },
                    {
                        "X": 0.8806583881378174,
                        "Y": 0.7751078009605408
                    },
                    {
                        "X": 0.8701879382133484,
                        "Y": 0.8282943367958069
                    },
                    {
                        "X": 0.8080818057060242,
                        "Y": 0.8055358529090881
                    }
                ]
            }
        },
        {
            "DetectedText": "2017-12-11",
            "Type": "WORD",
            "Id": 3,
            "ParentId": 0,
            "Confidence": 92.37554931640625,
            "Geometry": {
                "BoundingBox": {
                    "Width": 0.22637447714805603,
                    "Height": 0.05432388186454773,
                    "Left": 0.0,
                    "Top": 0.023208774626255035
                },
                "Polygon": [
                    {
                        "X": -0.003309968626126647,
                        "Y": 0.023071758449077606
                    },
                    {
                        "X": 0.2276492565870285,
                        "Y": 0.022581186145544052
                    },
                    {
                        "X": 0.22771142423152924,
                        "Y": 0.07706186175346375
                    },
                    {
                        "X": -0.0032478009816259146,
                        "Y": 0.0775524377822876
                    }
                ]
            }
        },
        {
            "DetectedText": "AM",
            "Type": "WORD",
            "Id": 4,
            "ParentId": 0,
            "Confidence": 94.78901672363281,
            "Geometry": {
                "BoundingBox": {
                    "Width": 0.04940098524093628,
                    "Height": 0.05495364964008331,
                    "Left": 0.24905183911323547,
                    "Top": 0.02335456758737564
                },
                "Polygon": [
                    {
                        "X": 0.24885280430316925,
                        "Y": 0.02353280782699585
                    },
                    {
                        "X": 0.29848819971084595,
                        "Y": 0.02319798432290554
                    },
                    {
                        "X": 0.29868605732917786,
                        "Y": 0.0777977854013443
                    },
                    {
                        "X": 0.24905067682266235,
                        "Y": 0.07813260704278946
                    }
                ]
            }
        },
        {
            "DetectedText": "03:54:",
            "Type": "WORD",
            "Id": 5,
            "ParentId": 0,
            "Confidence": 85.50056457519531,
            "Geometry": {
                "BoundingBox": {
                    "Width": 0.12072688341140747,
                    "Height": 0.05610337853431702,
                    "Left": 0.31969884037971497,
                    "Top": 0.022540541365742683
                },
                "Polygon": [
                    {
                        "X": 0.3157181739807129,
                        "Y": 0.022231442853808403
                    },
                    {
                        "X": 0.44413748383522034,
                        "Y": 0.022287877276539803
                    },
                    {
                        "X": 0.44412392377853394,
                        "Y": 0.07967235147953033
                    },
                    {
                        "X": 0.3157046139240265,
                        "Y": 0.07961591333150864
                    }
                ]
            }
        },
        {
            "DetectedText": "Entrance",
            "Type": "WORD",
            "Id": 6,
            "ParentId": 1,
            "Confidence": 97.85722351074219,
            "Geometry": {
                "BoundingBox": {
                    "Width": 0.21301677823066711,
                    "Height": 0.06805484741926193,
                    "Left": 0.0020401999354362488,
                    "Top": 0.11563543230295181
                },
                "Polygon": [
                    {
                        "X": 0.0018622541101649404,
                        "Y": 0.11625657230615616
                    },
                    {
                        "X": 0.21484370529651642,
                        "Y": 0.11555112898349762
                    },
                    {
                        "X": 0.21496298909187317,
                        "Y": 0.1825844794511795
                    },
                    {
                        "X": 0.0019815333653241396,
                        "Y": 0.18328991532325745
                    }
                ]
            }
        },
        {
            "DetectedText": "Jn",
            "Type": "WORD",
            "Id": 7,
            "ParentId": 2,
            "Confidence": 51.01042556762695,
            "Geometry": {
                "BoundingBox": {
                    "Width": 0.0742112398147583,
                    "Height": 0.07317781448364258,
                    "Left": 0.8068698644638062,
                    "Top": 0.7528828978538513
                },
                "Polygon": [
                    {
                        "X": 0.8185522556304932,
                        "Y": 0.752349317073822
                    },
                    {
                        "X": 0.8806583881378174,
                        "Y": 0.7751078009605408
                    },
                    {
                        "X": 0.8701879382133484,
                        "Y": 0.8282943367958069
                    },
                    {
                        "X": 0.8080818057060242,
                        "Y": 0.8055358529090881
                    }
                ]
            }
        }
    ]
}
