{
    "TextDetections": [
        {
            "DetectedText": "2017-12-11 AM 03:54",
            "Type": "LINE",
            "Id": 0,
            "Confidence": 91.67423248291016,
            "Geometry": {
                "BoundingBox": {
                    "Width": 0.44477349519729614,
                    "Height": 0.05762185528874397,
                    "Left": -0.0031814714893698692,
                    "Top": 0.021280556917190552
                },
                "Polygon": [
                    {
                        "X": -0.0031814714893698692,
                        "Y": 0.021280556917190552
                    },
                    {
                        "X": 0.4415920078754425,
                        "Y": 0.022305475547909737
                    },
                    {
                        "X": 0.44152069091796875,
                        "Y": 0.07992733269929886
                    },
                    {
                        "X": -0.00325280474498868,
                        "Y": 0.07890241593122482
                    }
                ]
            }
        },
        {
            "DetectedText": "Entrance",
            "Type": "LINE",
            "Id": 1,
            "Confidence": 97.9314956665039,
            "Geometry": {
                "BoundingBox": {
                    "Width": 0.2130553424358368,
                    "Height": 0.06704389303922653,
                    "Left": 0.0017148434417322278,
                    "Top": 0.11634903401136398
                },
                "Polygon": [
                    {
                        "X": 0.0017148434417322278,
                        "Y": 0.11634903401136398
                    },
                    {
                        "X": 0.21477018296718597,
                        "Y": 0.11539803445339203
                    },
                    {
                        "X": 0.2149309515953064,
                        "Y": 0.18244192004203796
                    },
                    {
                        "X": 0.0018756120698526502,
                        "Y": 0.18339292705059052
                    }
                ]
            }
        },
        {
            "DetectedText": "ate",
            "Type": "LINE",
            "Id": 2,
            "Confidence": 54.687965393066406,
            "Geometry": {
                "BoundingBox": {
                    "Width": 0.08364349603652954,
                    "Height": 0.07472237944602966,
                    "Left": 0.6017444133758545,
                    "Top": 0.5705508589744568
                },
                "Polygon": [
                    {
                        "X": 0.6017444133758545,
                        "Y": 0.5705508589744568
                    },
                    {
                        "X": 0.685387909412384,
                        "Y": 0.6119873523712158
                    },
                    {
                        "X": 0.6655015349388123,
                        "Y": 0.6867097616195679
                    },
                    {
                        "X": 0.5818580389022827,
                        "Y": 0.6452732682228088
                    }
                ]
            }
        },
        {
            "DetectedText": "2017-12-11",
            "Type": "WORD",
            "Id": 3,
            "ParentId": 0,
            "Confidence": 89.77288055419922,
            "Geometry": {
                "BoundingBox": {
                    "Width": 0.22603043913841248,
                    "Height": 0.05464373901486397,
                    "Left": 0.0,
                    "Top": 0.022892674431204796
                },
                "Polygon": [
                    {
                        "X": -0.0031833790708333254,
                        "Y": 0.022821413353085518
                    },
                    {
                        "X": 0.2273453027009964,
                        "Y": 0.022248655557632446
                    },
                    {
                        "X": 0.22741837799549103,
                        "Y": 0.0770014077425003
                    },
                    {
                        "X": -0.0031102977227419615,
                        "Y": 0.07757416367530823
                    }
                ]
            }
        },
        {
            "DetectedText": "AM",
            "Type": "WORD",
            "Id": 4,
            "ParentId": 0,
            "Confidence": 95.99508666992188,
            "Geometry": {
                "BoundingBox": {
                    "Width": 0.04963189363479614,
                    "Height": 0.0550992377102375,
                    "Left": 0.24882033467292786,
                    "Top": 0.023534780368208885
                },
                "Polygon": [
                    {
                        "X": 0.24853502213954926,
                        "Y": 0.023784151300787926
                    },
                    {
                        "X": 0.2985955774784088,
                        "Y": 0.02316158264875412
                    },
                    {
                        "X": 0.2989627420902252,
                        "Y": 0.07811621576547623
                    },
                    {
                        "X": 0.24890217185020447,
                        "Y": 0.07873878628015518
                    }
                ]
            }
        },
        {
            "DetectedText": "03:54",
            "Type": "WORD",
            "Id": 5,
            "ParentId": 0,
            "Confidence": 89.25472259521484,
            "Geometry": {
                "BoundingBox": {
                    "Width": 0.11763834953308105,
                    "Height": 0.0558379627764225,
                    "Left": 0.3198793828487396,
                    "Top": 0.02271854504942894
                },
                "Polygon": [
                    {
                        "X": 0.3155810534954071,
                        "Y": 0.022116689011454582
                    },
                    {
                        "X": 0.4415670931339264,
                        "Y": 0.02230541780591011
                    },
                    {
                        "X": 0.4415208101272583,
                        "Y": 0.0798257440328598
                    },
                    {
                        "X": 0.315534770488739,
                        "Y": 0.07963701337575912
                    }
                ]
            }
        },
        {
            "DetectedText": "Entrance",
            "Type": "WORD",
            "Id": 6,
            "ParentId": 1,
            "Confidence": 97.9314956665039,
            "Geometry": {
                "BoundingBox": {
                    "Width": 0.21305373311042786,
                    "Height": 0.06830295920372009,
                    "Left": 0.001950189471244812,
                    "Top": 0.11551089584827423
                },
                "Polygon": [
                    {
                        "X": 0.0017148434417322278,
                        "Y": 0.11634903401136398
                    },
                    {
                        "X": 0.21477018296718597,
                        "Y": 0.11539803445339203
                    },
                    {
                        "X": 0.2149309515953064,
                        "Y": 0.18244192004203796
                    },
                    {
                        "X": 0.0018756120698526502,
                        "Y": 0.18339292705059052
                    }
                ]
            }
        },
        {
            "DetectedText": "ate",
            "Type": "WORD",
            "Id": 7,
            "ParentId": 2,
            "Confidence": 54.687965393066406,
            "Geometry": {
                "BoundingBox": {
                    "Width": 0.10003626346588135,
                    "Height": 0.11407470703125,
                    "Left": 0.5860490798950195,
                    "Top": 0.5708662867546082
                },
                "Polygon": [
                    {
                        "X": 0.6017444133758545,
                        "Y": 0.5705508589744568
                    },
                    {
                        "X": 0.685387909412384,
                        "Y": 0.6119873523712158
                    },
                    {
                        "X": 0.6655015349388123,
                        "Y": 0.6867097616195679
                    },
                    {
                        "X": 0.5818580389022827,
                        "Y": 0.6452732682228088
                    }
                ]
            }
        }
    ]
}
