{
    "TextDetections": [
        {
            "DetectedText": "2017-12-11 AM 3:54: 40",
            "Type": "LINE",
            "Id": 0,
            "Confidence": 88.39598083496094,
            "Geometry": {
                "BoundingBox": {
                    "Width": 0.5054241418838501,
                    "Height": 0.05769328400492668,
                    "Left": -0.003218125319108367,
                    "Top": 0.02143332175910473
                },
                "Polygon": [
                    {
                        "X": -0.003218125319108367,
                        "Y": 0.02143332175910473
                    },
                    {
                        "X": 0.502206027507782,
                        "Y": 0.020886311307549477
                    },
                    {
                        "X": 0.5022395849227905,
                        "Y": 0.07857959717512131
                    },
                    {
                        "X": -0.0031845811754465103,
                        "Y": 0.07912660390138626
                    }
                ]
            }
        },
        {
            "DetectedText": "Entrance",
            "Type": "LINE",
            "Id": 1,
            "Confidence": 98.44268798828125,
            "Geometry": {
                "BoundingBox": {
                    "Width": 0.21289749443531036,
                    "Height": 0.066909559071064,
                    "Left": 0.0019977912306785583,
                    "Top": 0.11647703498601913
                },
                "Polygon": [
                    {
                        "X": 0.0019977912306785583,
                        "Y": 0.11647703498601913
                    },
                    {
                        "X": 0.21489529311656952,
                        "Y": 0.11598127335309982
                    },
                    {
                        "X": 0.21497899293899536,
                        "Y": 0.18289083242416382
                    },
                    {
                        "X": 0.0020814950112253428,
                        "Y": 0.18338659405708313
                    }
                ]
            }
        },
        {
            "DetectedText": "2017-12-11",
            "Type": "WORD",
            "Id": 2,
            "ParentId": 0,
            "Confidence": 93.885498046875,
            "Geometry": {
                "BoundingBox": {
                    "Width": 0.22579596936702728,
                    "Height": 0.05448511242866516,
                    "Left": 0.0,
                    "Top": 0.023097647354006767
                },
                "Polygon": [
                    {
                        "X": -0.003217205638065934,
                        "Y": 0.023015238344669342
                    },
                    {
                        "X": 0.22708089649677277,
                        "Y": 0.022539786994457245
                    },
                    {
                        "X": 0.22714142501354218,
                        "Y": 0.07710802555084229
                    },
                    {
                        "X": -0.0031566841062158346,
                        "Y": 0.07758347690105438
                    }
                ]
            }
        },
        {
            "DetectedText": "AM",
            "Type": "WORD",
            "Id": 3,
            "ParentId": 0,
            "Confidence": 80.45291900634766,
            "Geometry": {
                "BoundingBox": {
                    "Width": 0.049878478050231934,
                    "Height": 0.055318333208560944,
                    "Left": 0.24879825115203857,
                    "Top": 0.0236477330327034
                },
                "Polygon": [
                    {
                        "X": 0.24860839545726776,
                        "Y": 0.023917624726891518
                    },
                    {
                        "X": 0.298838347196579,
                        "Y": 0.023642323911190033
                    },
                    {
                        "X": 0.29899945855140686,
                        "Y": 0.07835759222507477
                    },
                    {
                        "X": 0.24876950681209564,
                        "Y": 0.0786328911781311
                    }
                ]
            }
        },
        {
            "DetectedText": "3:54:",
            "Type": "WORD",
            "Id": 4,
            "ParentId": 0,
            "Confidence": 91.08965301513672,
            "Geometry": {
                "BoundingBox": {
                    "Width": 0.11192768812179565,
                    "Height": 0.057093679904937744,
                    "Left": 0.3367120027542114,
                    "Top": 0.021156108006834984
                },
                "Polygon": [
                    {
                        "X": 0.33516183495521545,
                        "Y": 0.021067099645733833
                    },
                    {
                        "X": 0.4489153027534485,
                        "Y": 0.021198756992816925
                    },
                    {
                        "X": 0.448879599571228,
                        "Y": 0.07863734662532806
                    },
                    {
                        "X": 0.335126131772995,
                        "Y": 0.07850568741559982
                    }
                ]
            }
        },
        {
            "DetectedText": "40",
            "Type": "WORD",
            "Id": 5,
            "ParentId": 0,
            "Confidence": 88.15581512451172,
            "Geometry": {
                "BoundingBox": {
                    "Width": 0.049303293228149414,
                    "Height": 0.05389340594410896,
                    "Left": 0.4537771940231323,
                    "Top": 0.02321035787463188
                },
                "Polygon": [
                    {
                        "X": 0.45431414246559143,
                        "Y": 0.022256409749388695
                    },
                    {
                        "X": 0.5022068619728088,
                        "Y": 0.022318508476018906
                    },
                    {
                        "X": 0.5021682977676392,
                        "Y": 0.07768277823925018
                    },
                    {
                        "X": 0.45427557826042175,
                        "Y": 0.07762067764997482
                    }
                ]
            }
        },
        {
            "DetectedText": "Entrance",
            "Type": "WORD",
            "Id": 6,
            "ParentId": 1,
            "Confidence": 98.44268798828125,
            "Geometry": {
                "BoundingBox": {
                    "Width": 0.21297208964824677,
                    "Height": 0.06771817803382874,
                    "Left": 0.002124592661857605,
                    "Top": 0.1160336583852768
                },
                "Polygon": [
                    {
                        "X": 0.0019977912306785583,
                        "Y": 0.11647703498601913
                    },
                    {
                        "X": 0.21489529311656952,
                        "Y": 0.11598127335309982
                    },
                    {
                        "X": 0.21497899293899536,
                        "Y": 0.18289083242416382
                    },
                    {
                        "X": 0.0020814950112253428,
                        "Y": 0.18338659405708313
                    }
                ]
            }
        }
    ]
}
