{
    "TextDetections": [
        {
            "DetectedText": "2017-12-11 AM 03: 54:51",
            "Type": "LINE",
            "Id": 0,
            "Confidence": 90.29671478271484,
            "Geometry": {
                "BoundingBox": {
                    "Width": 0.49394261837005615,
                    "Height": 0.060661811381578445,
                    "Left": -0.003001940669491887,
                    "Top": 0.02009149268269539
                },
                "Polygon": [
                    {
                        "X": -0.003001940669491887,
                        "Y": 0.02009149268269539
                    },
                    {
                        "X": 0.4909406900405884,
                        "Y": 0.019211851060390472
                    },
                    {
                        "X": 0.4909987151622772,
                        "Y": 0.07987366616725922
                    },
                    {
                        "X": -0.0029439046047627926,
                        "Y": 0.08075330406427383
                    }
                ]
            }
        },
        {
            "DetectedText": "Entrance",
            "Type": "LINE",
            "Id": 1,
            "Confidence": 98.98628234863281,
            "Geometry": {
                "BoundingBox": {
                    "Width": 0.21235251426696777,
                    "Height": 0.06652690470218658,
                    "Left": 0.002221603412181139,
                    "Top": 0.116397425532341
                },
                "Polygon": [
                    {
                        "X": 0.002221603412181139,
                        "Y": 0.116397425532341
                    },
                    {
                        "X": 0.21457411348819733,
                        "Y": 0.11561427265405655
                    },
                    {
                        "X": 0.2147059142589569,
                        "Y": 0.18214118480682373
                    },
                    {
                        "X": 0.0023534109350293875,
                        "Y": 0.1829243302345276
                    }
                ]
            }
        },
        {
            "DetectedText": "2017-12-11",
            "Type": "WORD",
            "Id": 2,
            "ParentId": 0,
            "Confidence": 92.23794555664062,
            "Geometry": {
                "BoundingBox": {
                    "Width": 0.22656138241291046,
                    "Height": 0.05405380576848984,
                    "Left": 0.0,
                    "Top": 0.02352312207221985
                },
                "Polygon": [
                    {
                        "X": -0.0029985730070620775,
                        "Y": 0.023611513897776604
                    },
                    {
                        "X": 0.22785638272762299,
                        "Y": 0.022957416251301765
                    },
                    {
                        "X": 0.22793851792812347,
                        "Y": 0.07691564410924911
                    },
                    {
                        "X": -0.002916440600529313,
                        "Y": 0.07756973803043365
                    }
                ]
            }
        },
        {
            "DetectedText": "AM",
            "Type": "WORD",
            "Id": 3,
            "ParentId": 0,
            "Confidence": 96.26741790771484,
            "Geometry": {
                "BoundingBox": {
                    "Width": 0.04954905807971954,
                    "Height": 0.05418575927615166,
                    "Left": 0.24904339015483856,
                    "Top": 0.0240852702409029
                },
                "Polygon": [
                    {
                        "X": 0.24880041182041168,
                        "Y": 0.024327093735337257
                    },
                    {
                        "X": 0.298757940530777,
                        "Y": 0.023967644199728966
                    },
                    {
                        "X": 0.29896607995033264,
                        "Y": 0.07781747728586197
                    },
                    {
                        "X": 0.24900856614112854,
                        "Y": 0.07817693054676056
                    }
                ]
            }
        },
        {
            "DetectedText": "03:",
            "Type": "WORD",
            "Id": 4,
            "ParentId": 0,
            "Confidence": 83.50528717041016,
            "Geometry": {
                "BoundingBox": {
                    "Width": 0.06784403324127197,
                    "Height": 0.05527995526790619,
                    "Left": 0.31839320063591003,
                    "Top": 0.022444183006882668
                },
                "Polygon": [
                    {
                        "X": 0.3175417482852936,
                        "Y": 0.02003936655819416
                    },
                    {
                        "X": 0.3881604075431824,
                        "Y": 0.022111311554908752
                    },
                    {
                        "X": 0.3872491121292114,
                        "Y": 0.07992617040872574
                    },
                    {
                        "X": 0.31663045287132263,
                        "Y": 0.077854223549366
                    }
                ]
            }
        },
        {
            "DetectedText": "54:51",
            "Type": "WORD",
            "Id": 5,
            "ParentId": 0,
            "Confidence": 89.17620849609375,
            "Geometry": {
                "BoundingBox": {
                    "Width": 0.1041262149810791,
                    "Height": 0.05869106948375702,
                    "Left": 0.3848686218261719,
                    "Top": 0.019631072878837585
                },
                "Polygon": [
                    {
                        "X": 0.38403239846229553,
                        "Y": 0.019402239471673965
                    },
                    {
                        "X": 0.4909411370754242,
                        "Y": 0.019677184522151947
                    },
                    {
                        "X": 0.49085795879364014,
                        "Y": 0.07987391203641891
                    },
                    {
                        "X": 0.3839492201805115,
                        "Y": 0.07959897071123123
                    }
                ]
            }
        },
        {
            "DetectedText": "Entrance",
            "Type": "WORD",
            "Id": 6,
            "ParentId": 1,
            "Confidence": 98.98628234863281,
            "Geometry": {
                "BoundingBox": {
                    "Width": 0.21233542263507843,
                    "Height": 0.0676618218421936,
                    "Left": 0.0024936646223068237,
                    "Top": 0.11568273603916168
                },
                "Polygon": [
                    {
                        "X": 0.002221603412181139,
                        "Y": 0.116397425532341
                    },
                    {
                        "X": 0.21457411348819733,
                        "Y": 0.11561427265405655
                    },
                    {
                        "X": 0.2147059142589569,
                        "Y": 0.18214118480682373
                    },
                    {
                        "X": 0.0023534109350293875,
                        "Y": 0.1829243302345276
                    }
                ]
            }
        }
    ]
}
