{
    "TextDetections": [
        {
            "DetectedText": "2017-12-11 AM 03:54:",
            "Type": "LINE",
            "Id": 0,
            "Confidence": 90.56305694580078,
            "Geometry": {
                "BoundingBox": {
                    "Width": 0.44610869884490967,
                    "Height": 0.0577949620783329,
                    "Left": -0.0029702219180762768,
                    "Top": 0.021525289863348007
                },
                "Polygon": [
                    {
                        "X": -0.0029702219180762768,
                        "Y": 0.021525289863348007
                    },
                    {
                        "X": 0.4431384801864624,
                        "Y": 0.021973567083477974
                    },
                    {
                        "X": 0.4431072771549225,
                        "Y": 0.07976853102445602
                    },
                    {
                        "X": -0.0030014216899871826,
                        "Y": 0.07932025194168091
                    }
                ]
            }
        },
        {
            "DetectedText": "Entrance",
            "Type": "LINE",
            "Id": 1,
            "Confidence": 98.95923614501953,
            "Geometry": {
                "BoundingBox": {
                    "Width": 0.21232685446739197,
                    "Height": 0.06670565903186798,
                    "Left": 0.0023764672223478556,
                    "Top": 0.1163862869143486
                },
                "Polygon": [
                    {
                        "X": 0.0023764672223478556,
                        "Y": 0.1163862869143486
                    },
                    {
                        "X": 0.21470332145690918,
                        "Y": 0.11519575119018555
                    },
                    {
                        "X": 0.21490424871444702,
                        "Y": 0.18190141022205353
                    },
                    {
                        "X": 0.0025774016976356506,
                        "Y": 0.18309195339679718
                    }
                ]
            }
        },
        {
            "DetectedText": "2017-12-11",
            "Type": "WORD",
            "Id": 2,
            "ParentId": 0,
            "Confidence": 87.150390625,
            "Geometry": {
                "BoundingBox": {
                    "Width": 0.2260497808456421,
                    "Height": 0.05436376854777336,
                    "Left": 0.0,
                    "Top": 0.02321137860417366
                },
                "Polygon": [
                    {
                        "X": -0.002971224021166563,
                        "Y": 0.023381587117910385
                    },
                    {
                        "X": 0.22733093798160553,
                        "Y": 0.02260776236653328
                    },
                    {
                        "X": 0.22742879390716553,
                        "Y": 0.07682270556688309
                    },
                    {
                        "X": -0.002873361110687256,
                        "Y": 0.07759653031826019
                    }
                ]
            }
        },
        {
            "DetectedText": "AM",
            "Type": "WORD",
            "Id": 3,
            "ParentId": 0,
            "Confidence": 96.78569793701172,
            "Geometry": {
                "BoundingBox": {
                    "Width": 0.049448490142822266,
                    "Height": 0.05482743680477142,
                    "Left": 0.24901220202445984,
                    "Top": 0.023679792881011963
                },
                "Polygon": [
                    {
                        "X": 0.24879668653011322,
                        "Y": 0.02378123253583908
                    },
                    {
                        "X": 0.29866090416908264,
                        "Y": 0.0234480332583189
                    },
                    {
                        "X": 0.2988574802875519,
                        "Y": 0.07820845395326614
                    },
                    {
                        "X": 0.24899326264858246,
                        "Y": 0.07854165136814117
                    }
                ]
            }
        },
        {
            "DetectedText": "03:54:",
            "Type": "WORD",
            "Id": 4,
            "ParentId": 0,
            "Confidence": 87.75308227539062,
            "Geometry": {
                "BoundingBox": {
                    "Width": 0.11837869882583618,
                    "Height": 0.05566820874810219,
                    "Left": 0.3207125961780548,
                    "Top": 0.022582462057471275
                },
                "Polygon": [
                    {
                        "X": 0.3168101906776428,
                        "Y": 0.02220492623746395
                    },
                    {
                        "X": 0.44305089116096497,
                        "Y": 0.02197347953915596
                    },
                    {
                        "X": 0.4431074559688568,
                        "Y": 0.07941023260354996
                    },
                    {
                        "X": 0.31686675548553467,
                        "Y": 0.0796416774392128
                    }
                ]
            }
        },
        {
            "DetectedText": "Entrance",
            "Type": "WORD",
            "Id": 5,
            "ParentId": 1,
            "Confidence": 98.95923614501953,
            "Geometry": {
                "BoundingBox": {
                    "Width": 0.21245723962783813,
                    "Height": 0.06820770353078842,
                    "Left": 0.0025328025221824646,
                    "Top": 0.11533082276582718
                },
                "Polygon": [
                    {
                        "X": 0.0023764672223478556,
                        "Y": 0.1163862869143486
                    },
                    {
                        "X": 0.21470332145690918,
                        "Y": 0.11519575119018555
                    },
                    {
                        "X": 0.21490424871444702,
                        "Y": 0.18190141022205353
                    },
                    {
                        "X": 0.0025774016976356506,
                        "Y": 0.18309195339679718
                    }
                ]
            }
        }
    ]
}
