{
    "TextDetections": [
        {
            "DetectedText": "2017-12-11 AM 03:54",
            "Type": "LINE",
            "Id": 0,
            "Confidence": 92.77668762207031,
            "Geometry": {
                "BoundingBox": {
                    "Width": 0.4365418553352356,
                    "Height": 0.058213863521814346,
                    "Left": -0.0028497774619609118,
                    "Top": 0.020989995449781418
                },
                "Polygon": [
                    {
                        "X": -0.0028497774619609118,
                        "Y": 0.020989995449781418
                    },
                    {
                        "X": 0.4336920976638794,
                        "Y": 0.021719183772802353
                    },
                    {
                        "X": 0.43363985419273376,
                        "Y": 0.0799330472946167
                    },
                    {
                        "X": -0.0029020162764936686,
                        "Y": 0.07920385897159576
                    }
                ]
            }
        },
        {
            "DetectedText": "Entrance",
            "Type": "LINE",
            "Id": 1,
            "Confidence": 98.20232391357422,
            "Geometry": {
                "BoundingBox": {
                    "Width": 0.21327070891857147,
                    "Height": 0.06667619943618774,
                    "Left": 0.0015425576129928231,
                    "Top": 0.11670491844415665
                },
                "Polygon": [
                    {
                        "X": 0.0015425576129928231,
                        "Y": 0.11670491844415665
                    },
                    {
                        "X": 0.2148132622241974,
                        "Y": 0.11580497026443481
                    },
                    {
                        "X": 0.21496441960334778,
                        "Y": 0.18248116970062256
                    },
                    {
                        "X": 0.001693708705715835,
                        "Y": 0.183381125330925
                    }
                ]
            }
        },
        {
            "DetectedText": "2017-12-11",
            "Type": "WORD",
            "Id": 2,
            "ParentId": 0,
            "Confidence": 89.23595428466797,
            "Geometry": {
                "BoundingBox": {
                    "Width": 0.2264884114265442,
                    "Height": 0.05455666780471802,
                    "Left": 0.0,
                    "Top": 0.02298608608543873
                },
                "Polygon": [
                    {
                        "X": -0.0028515118174254894,
                        "Y": 0.022922787815332413
                    },
                    {
                        "X": 0.22771452367305756,
                        "Y": 0.022394774481654167
                    },
                    {
                        "X": 0.227781742811203,
                        "Y": 0.077028289437294
                    },
                    {
                        "X": -0.0027842973358929157,
                        "Y": 0.0775563046336174
                    }
                ]
            }
        },
        {
            "DetectedText": "AM",
            "Type": "WORD",
            "Id": 3,
            "ParentId": 0,
            "Confidence": 96.58662414550781,
            "Geometry": {
                "BoundingBox": {
                    "Width": 0.04922686517238617,
                    "Height": 0.05515230447053909,
                    "Left": 0.2492266744375229,
                    "Top": 0.02359314262866974
                },
                "Polygon": [
                    {
                        "X": 0.2488982081413269,
                        "Y": 0.02380186878144741
                    },
                    {
                        "X": 0.2986232042312622,
                        "Y": 0.023325921967625618
                    },
                    {
                        "X": 0.2989060878753662,
                        "Y": 0.07834197580814362
                    },
                    {
                        "X": 0.2491811066865921,
                        "Y": 0.07881791889667511
                    }
                ]
            }
        },
        {
            "DetectedText": "03:54",
            "Type": "WORD",
            "Id": 4,
            "ParentId": 0,
            "Confidence": 92.5074691772461,
            "Geometry": {
                "BoundingBox": {
                    "Width": 0.10992580652236938,
                    "Height": 0.05618065595626831,
                    "Left": 0.3194752335548401,
                    "Top": 0.022228308022022247
                },
                "Polygon": [
                    {
                        "X": 0.31473931670188904,
                        "Y": 0.02157149463891983
                    },
                    {
                        "X": 0.43367868661880493,
                        "Y": 0.021719161421060562
                    },
                    {
                        "X": 0.43363988399505615,
                        "Y": 0.07988204061985016
                    },
                    {
                        "X": 0.31470051407814026,
                        "Y": 0.07973437756299973
                    }
                ]
            }
        },
        {
            "DetectedText": "Entrance",
            "Type": "WORD",
            "Id": 5,
            "ParentId": 1,
            "Confidence": 98.20232391357422,
            "Geometry": {
                "BoundingBox": {
                    "Width": 0.21326367557048798,
                    "Height": 0.06792950630187988,
                    "Left": 0.0017749890685081482,
                    "Top": 0.11588245630264282
                },
                "Polygon": [
                    {
                        "X": 0.0015425576129928231,
                        "Y": 0.11670491844415665
                    },
                    {
                        "X": 0.2148132622241974,
                        "Y": 0.11580497026443481
                    },
                    {
                        "X": 0.21496441960334778,
                        "Y": 0.18248116970062256
                    },
                    {
                        "X": 0.001693708705715835,
                        "Y": 0.183381125330925
                    }
                ]
            }
        }
    ]
}
